simplejsoncsvdb/__init__.py
simplejsoncsvdb/database.py
simplejsoncsvdb/exceptions.py
simplejsoncsvdb-0.1.1.dist-info/METADATA
simplejsoncsvdb-0.1.1.dist-info/WHEEL
simplejsoncsvdb-0.1.1.dist-info/top_level.txt
simplejsoncsvdb-0.1.1.dist-info/RECORD
